pykube/__init__.py
pykube/config.py
pykube/exceptions.py
pykube/http.py
pykube/mixins.py
pykube/objects.py
pykube/query.py
pykube/rolling_updater.py
pykube/utils.py
pykube/contrib/__init__.py
pykube/contrib/httpie_plugin.py
test/__init__.py
test/fixtures.py
test/test_authexec.py
test/test_config.py
test/test_http.py
test/test_httpclient.py
pykubeks-0.1.0.dist-info/LICENSE
pykubeks-0.1.0.dist-info/METADATA
pykubeks-0.1.0.dist-info/WHEEL
pykubeks-0.1.0.dist-info/entry_points.txt
pykubeks-0.1.0.dist-info/top_level.txt
pykubeks-0.1.0.dist-info/RECORD
