Metadata-Version: 2.1
Name: pykubeks
Version: 0.1.0
Summary: Python client library for Kubernetes w/ EKS support
Home-page: https://github.com/steinnes/pykubeks
Author: Steinn Eldjarn Sigurdarson
Author-email: steinnes@gmail.com
License: Apache
Platform: UNKNOWN
Classifier: Development Status :: 3 - Alpha
Classifier: Environment :: Web Environment
Classifier: Intended Audience :: Developers
Classifier: License :: OSI Approved :: Apache Software License
Classifier: Operating System :: OS Independent
Classifier: Programming Language :: Python
Requires-Dist: requests (>=2.12)
Requires-Dist: PyYAML
Requires-Dist: six (>=1.10.0)
Requires-Dist: tzlocal
Provides-Extra: gcp
Requires-Dist: google-auth ; extra == 'gcp'
Requires-Dist: jsonpath-ng ; extra == 'gcp'
